CHANGES.txt
LICENSE.txt
MANIFEST.in
README.md
development.ini
sample-data.json
setup.cfg
setup.py
examples/development.ini
examples/production.ini
examples/pyrone-blog-nginx-uwsgi-ssl.conf
examples/pyrone-blog-nginx-uwsgi.conf
examples/pyrone-uwsgi.ini
pyrone/__init__.py
pyrone/resources.py
pyrone/subscribers.py
pyrone/tests.py
pyrone/version.py
pyrone.egg-info/PKG-INFO
pyrone.egg-info/SOURCES.txt
pyrone.egg-info/dependency_links.txt
pyrone.egg-info/entry_points.txt
pyrone.egg-info/not-zip-safe
pyrone.egg-info/requires.txt
pyrone.egg-info/top_level.txt
pyrone/lib/PyRSS2Gen.py
pyrone/lib/__init__.py
pyrone/lib/auth.py
pyrone/lib/cache.py
pyrone/lib/helpers.py
pyrone/lib/httpcode.py
pyrone/lib/jsonhttpresponse.py
pyrone/lib/lang.py
pyrone/lib/markup.py
pyrone/lib/notifications.py
pyrone/locale/en/LC_MESSAGES/pyrone.mo
pyrone/locale/ru/LC_MESSAGES/pyrone.mo
pyrone/models/__init__.py
pyrone/models/article.py
pyrone/models/config.py
pyrone/models/file.py
pyrone/models/meta.py
pyrone/models/user.py
pyrone/scripts/__init__.py
pyrone/scripts/pyronedbinit.py
pyrone/static/article-markup-tip-en.html
pyrone/static/article-markup-tip-ru.html
pyrone/static/comment-markup-tip-en.html
pyrone/static/comment-markup-tip-ru.html
pyrone/static/themes-notes-en.html
pyrone/static/themes-notes-ru.html
pyrone/static/font-awesome/version.txt
pyrone/static/font-awesome/css/font-awesome.css
pyrone/static/font-awesome/css/font-awesome.min.css
pyrone/static/font-awesome/fonts/FontAwesome.otf
pyrone/static/font-awesome/fonts/fontawesome-webfont.eot
pyrone/static/font-awesome/fonts/fontawesome-webfont.svg
pyrone/static/font-awesome/fonts/fontawesome-webfont.woff
pyrone/static/images/sample-image.png
pyrone/static/lang/en.js
pyrone/static/lang/ru.js
pyrone/static/scripts/admin.js
pyrone/static/scripts/blog.js
pyrone/static/scripts/jquery/field-selection.js
pyrone/static/styles/blog.regolit.com/blog.css
pyrone/static/styles/default/blog.css
pyrone/static/styles/default/images/broom.png
pyrone/static/styles/default/images/edit.png
pyrone/static/styles/default/images/twitter-icon.png
pyrone/static/styles/green/blog.css
pyrone/templates/403.mako
pyrone/templates/404.mako
pyrone/templates/admin/base.mako
