Metadata-Version: 1.1
Name: pyrone
Version: 1.4.2
Summary: pyrone
Home-page: https://github.com/sigsergv/pyrone
Author: Sergey Stolyarov
Author-email: sergei@regolit.com
License: New BSD License
Keywords: web wsgi bfg pylons pyramid
Platform: UNKNOWN
Classifier: Development Status :: 4 - Beta
Classifier: Programming Language :: Python
Classifier: Intended Audience :: Developers
Classifier: Programming Language :: Python :: 3.4
Classifier: Framework :: Pyramid
Classifier: License :: OSI Approved :: BSD License
Classifier: Topic :: Internet :: WWW/HTTP
Classifier: Topic :: Internet :: WWW/HTTP :: WSGI :: Application
Classifier: Topic :: Internet :: WWW/HTTP :: Site Management
Classifier: Topic :: Internet :: WWW/HTTP :: Dynamic Content
